odoo8_addon_l10n_fi_payment_terms-8.0.1.0.0-py2.7-nspkg.pth
odoo8_addon_l10n_fi_payment_terms-8.0.1.0.0.dist-info/DESCRIPTION.rst
odoo8_addon_l10n_fi_payment_terms-8.0.1.0.0.dist-info/METADATA
odoo8_addon_l10n_fi_payment_terms-8.0.1.0.0.dist-info/RECORD
odoo8_addon_l10n_fi_payment_terms-8.0.1.0.0.dist-info/WHEEL
odoo8_addon_l10n_fi_payment_terms-8.0.1.0.0.dist-info/metadata.json
odoo8_addon_l10n_fi_payment_terms-8.0.1.0.0.dist-info/namespace_packages.txt
odoo8_addon_l10n_fi_payment_terms-8.0.1.0.0.dist-info/top_level.txt
odoo_addons/l10n_fi_payment_terms/README.rst
odoo_addons/l10n_fi_payment_terms/__init__.py
odoo_addons/l10n_fi_payment_terms/__openerp__.py
odoo_addons/l10n_fi_payment_terms/data/payment_terms_finnish.xml
odoo_addons/l10n_fi_payment_terms/i18n/fi.po
odoo_addons/l10n_fi_payment_terms/models/__init__.py
odoo_addons/l10n_fi_payment_terms/models/payment_term.py
odoo_addons/l10n_fi_payment_terms/static/description/icon.png
